Metadata-Version: 2.1
Name: jikan4snek
Version: 1.0.2
Summary: Python client for Jikan.moe
Home-page: https://github.com/ScathachGrip/jikan4snek
Author: sinkaroid
Author-email: anakmancasan@gmail.com
License: MIT
Project-URL: CI, https://github.com/ScathachGrip/jikan4snek/actions
Project-URL: Funding, https://github.com/sponsors/sinkaroid
Project-URL: Issue tracker, https://github.com/ScathachGrip/jikan4snek/issues/new/choose
Project-URL: Documentation, https://ScathachGrip.github.io/jikan4snek
Keywords: jikan,myanimelist,mal
Classifier: Framework :: AsyncIO
Classifier: Development Status :: 3 - Alpha
Classifier: Intended Audience :: Developers
Classifier: License :: OSI Approved :: MIT License
Classifier: Natural Language :: English
Classifier: Operating System :: OS Independent
Classifier: Programming Language :: Python :: 3.7
Classifier: Programming Language :: Python :: 3.8
Classifier: Programming Language :: Python :: 3.9
Classifier: Programming Language :: Python :: 3.10
Classifier: Topic :: Games/Entertainment
Classifier: Topic :: Internet :: WWW/HTTP
Classifier: Topic :: Software Development :: Libraries
License-File: LICENSE
